[
  {
    "json_class": "MusicAlbum",
    "id": 801,
    "on_spotify": true,
    "publish_date": "2021-01-01",
    "genre": { "json_class": "Genre", "id": 506, "name": "action" },
    "author": null
  },
  {
    "json_class": "MusicAlbum",
    "id": 551,
    "on_spotify": false,
    "publish_date": "2022-02-02",
    "genre": { "json_class": "Genre", "id": 506, "name": "action" },
    "author": null
  },
  {
    "json_class": "MusicAlbum",
    "id": 30,
    "on_spotify": true,
    "publish_date": "2023-03-03",
    "genre": { "json_class": "Genre", "id": 586, "name": "folk" },
    "author": null
  }
]
